Application/ChatManager.py
Application/ConnectionManager.py
Application/__init__.py
Application/__main__.py
FrodoKEM/__init__.py
FrodoKEM/frodo640/__init__.py
FrodoKEM/frodo640/api_frodo640.py
FrodoKEM/src/__init__.py
FrodoKEM/src/config.py
FrodoKEM/src/frodo_macrify.py
FrodoKEM/src/kem.py
FrodoKEM/src/noise.py
FrodoKEM/src/util.py
FrodoKEM/src/sha3/__init__.py
FrodoKEM/src/sha3/shafips202.py
frodokem_with_chat-1.0.4.dist-info/LICENSE
frodokem_with_chat-1.0.4.dist-info/METADATA
frodokem_with_chat-1.0.4.dist-info/WHEEL
frodokem_with_chat-1.0.4.dist-info/top_level.txt
frodokem_with_chat-1.0.4.dist-info/RECORD
