Metadata-Version: 2.1
Name: frodokem-with-chat
Version: 1.0.4
Summary: FrodoKEM implementation and presentation application
Home-page: https://github.com/PrzemyslawSamsel/AgainstQuantum
Author: 0xCA7
Author-email: samselprzemyslaw@gmail.com
License: UNKNOWN
Platform: UNKNOWN
Classifier: Programming Language :: Python :: 3
Classifier: License :: OSI Approved :: MIT License
Classifier: Operating System :: OS Independent
Requires-Python: >=3.6
Requires-Dist: numpy
Requires-Dist: pycryptodome
